README.txt
setup.cfg
setup.py
bit/__init__.py
bit.recipe.python_for_android.egg-info/PKG-INFO
bit.recipe.python_for_android.egg-info/SOURCES.txt
bit.recipe.python_for_android.egg-info/dependency_links.txt
bit.recipe.python_for_android.egg-info/entry_points.txt
bit.recipe.python_for_android.egg-info/namespace_packages.txt
bit.recipe.python_for_android.egg-info/not-zip-safe
bit.recipe.python_for_android.egg-info/requires.txt
bit.recipe.python_for_android.egg-info/top_level.txt
bit/recipe/__init__.py
bit/recipe/python_for_android/__init__.py
bit/recipe/python_for_android/python_for_android