Metadata-Version: 1.0
Name: bit.recipe.python-for-android
Version: 0.0.2
Summary: bitfoundation python_for_android recipe
Home-page: http://www.python.org/pypi/bit.recipe.python_for_android
Author: Ryan Northey
Author-email: ryan@3ca.org.uk
License: GPL
Keywords: buildout
Platform: UNKNOWN
